rent_insider_payments/__init__.py
rent_insider_payments/asgi.py
rent_insider_payments/urls.py
rent_insider_payments/wsgi.py
rent_insider_payments/apps/__init__.py
rent_insider_payments/settings/__init__.py
rent_insider_payments/settings/ci.py
rent_insider_payments/settings/common.py
rent_insider_payments/settings/local.py
rent_insider_payments/settings/production.py
rent_insider_payments/settings/settings.py
rent_insider_payments/settings/staging.py
payments_romania2-1.0.dist-info/METADATA
payments_romania2-1.0.dist-info/WHEEL
payments_romania2-1.0.dist-info/top_level.txt
payments_romania2-1.0.dist-info/RECORD
